ok/__init__.cp312-win_amd64.pyd
ok/__init__.py
ok/__init__.pyi
ok/alas/__init__.py
ok/alas/emulator_base.py
ok/alas/emulator_windows.py
ok/alas/platform_windows.py
ok/alas/utils.py
ok/capture/__init__.py
ok/capture/adb/__init__.py
ok/capture/adb/deep.py
ok/capture/adb/minitouch.py
ok/capture/adb/nemu_ipc.py
ok/capture/adb/nemu_utils.py
ok/capture/adb/pool.py
ok/capture/adb/timer.py
ok/capture/adb/util.py
ok/capture/windows/__init__.py
ok/capture/windows/d3d11.py
ok/capture/windows/dump.py
ok/device/DeviceManager.py
ok/device/__init__.py
ok/device/capture.cp312-win_amd64.pyd
ok/device/intercation.py
ok/feature/Box.cp312-win_amd64.pyd
ok/feature/CompressCoco.py
ok/feature/Feature.py
ok/feature/FeatureSet.cp312-win_amd64.pyd
ok/feature/__init__.py
ok/gui/Communicate.py
ok/gui/MainWindow.py
ok/gui/MessageWindow.py
ok/gui/StartController.py
ok/gui/TabTitles.py
ok/gui/__init__.py
ok/gui/resources.py
ok/gui/about/AboutTab.py
ok/gui/about/HttpTextEdit.py
ok/gui/about/VersionCard.py
ok/gui/about/__init__.py
ok/gui/common/OKIcon.py
ok/gui/common/__init__.py
ok/gui/common/config.py
ok/gui/common/style_sheet.py
ok/gui/debug/DebugTab.py
ok/gui/debug/FrameWidget.py
ok/gui/debug/LogWindow.py
ok/gui/debug/Screenshot.py
ok/gui/debug/__init__.py
ok/gui/i18n/GettextTranslator.py
ok/gui/i18n/__init__.py
ok/gui/i18n/path.py
ok/gui/i18n/update.py
ok/gui/launcher/DownloadBar.py
ok/gui/launcher/LauncherWindow.py
ok/gui/launcher/LinksBar.py
ok/gui/launcher/RunBar.py
ok/gui/launcher/UpdateBar.py
ok/gui/launcher/__init__.py
ok/gui/overlay/OverlayWindow.py
ok/gui/overlay/__init__.py
ok/gui/qss/__init__.py
ok/gui/settings/GlobalConfigCard.py
ok/gui/settings/SettingTab.py
ok/gui/settings/__init__.py
ok/gui/start/SelectCaptureListView.py
ok/gui/start/StartCard.py
ok/gui/start/StartTab.py
ok/gui/start/__init__.py
ok/gui/tasks/ConfigCard.py
ok/gui/tasks/ConfigItemFactory.py
ok/gui/tasks/ConfigLabelAndWidget.py
ok/gui/tasks/LabelAndDoubleSpinBox.py
ok/gui/tasks/LabelAndDropDown.py
ok_script-1.0.45.dist-info/METADATA
ok_script-1.0.45.dist-info/WHEEL
ok_script-1.0.45.dist-info/top_level.txt
ok_script-1.0.45.dist-info/RECORD
